WeatherapibyAli/01d@2x.png
WeatherapibyAli/01n@2x.png
WeatherapibyAli/02d@2x.png
WeatherapibyAli/02n@2x.png
WeatherapibyAli/03d@2x.png
WeatherapibyAli/03n@2x.png
WeatherapibyAli/04d@2x.png
WeatherapibyAli/04n@2x.png
WeatherapibyAli/09d@2x.png
WeatherapibyAli/09n@2x.png
WeatherapibyAli/10d@2x.png
WeatherapibyAli/10n@2x.png
WeatherapibyAli/11d@2x.png
WeatherapibyAli/11n@2x.png
WeatherapibyAli/13d@2x.png
WeatherapibyAli/13n@2x.png
WeatherapibyAli/50d@2x.png
WeatherapibyAli/50n@2x.png
WeatherapibyAli/Layer 6.png
WeatherapibyAli/Layer 7.png
WeatherapibyAli/Rounded Rectangle 1.png
WeatherapibyAli/Rounded Rectangle 2 copy.png
WeatherapibyAli/Rounded Rectangle 2.png
WeatherapibyAli/Rounded Rectangle 3.png
WeatherapibyAli/__init__.py
WeatherapibyAli/logo.png
weatherapibyAli-9.0.0.dist-info/METADATA
weatherapibyAli-9.0.0.dist-info/WHEEL
weatherapibyAli-9.0.0.dist-info/top_level.txt
weatherapibyAli-9.0.0.dist-info/RECORD
