Metadata-Version: 2.1
Name: weatherapibyAli
Version: 9.0.0
Summary: Это Проект Weather App. This Project Weather App.
Home-page: https://github.com/alikushbaev/Weatherapp
Author: __init__
Author-email: jamshidkushbaev@gmail.com
Project-URL: Documentation, https://github.com/alikushbaev/Weatherapp
Classifier: Programming Language :: Python :: 3
Classifier: License :: OSI Approved :: MIT License
Classifier: Operating System :: OS Independent
Requires-Python: >=3.11
Requires-Dist: requests
Requires-Dist: datetime
Requires-Dist: pystray
Requires-Dist: pytz
Requires-Dist: geopy
Requires-Dist: pillow
Requires-Dist: timezonefinder
